tinys_srd/AbilityScores.py
tinys_srd/Alignments.py
tinys_srd/Backgrounds.py
tinys_srd/Classes.py
tinys_srd/Conditions.py
tinys_srd/DamageTypes.py
tinys_srd/Equipment.py
tinys_srd/EquipmentCategories.py
tinys_srd/Feats.py
tinys_srd/Features.py
tinys_srd/Languages.py
tinys_srd/Levels.py
tinys_srd/MagicItems.py
tinys_srd/MagicSchools.py
tinys_srd/Monsters.py
tinys_srd/Proficiencies.py
tinys_srd/Races.py
tinys_srd/RuleSections.py
tinys_srd/Rules.py
tinys_srd/Skills.py
tinys_srd/Spells.py
tinys_srd/Subclasses.py
tinys_srd/Subraces.py
tinys_srd/Traits.py
tinys_srd/WeaponProperties.py
tinys_srd/__init__.py
tinys_srd/entry_builder.py
tinys_srd-1.0.0.dist-info/LICENSE
tinys_srd-1.0.0.dist-info/METADATA
tinys_srd-1.0.0.dist-info/WHEEL
tinys_srd-1.0.0.dist-info/top_level.txt
tinys_srd-1.0.0.dist-info/RECORD
