Metadata-Version: 2.1
Name: tinys_srd
Version: 1.0.0
Summary: A local SRD for offline access.
Project-URL: Homepage, https://github.com/BigBrainTime/tinys-srd
Project-URL: Issues, https://github.com/BigBrainTime/tinys-srd/issuess
Classifier: Programming Language :: Python :: 3
Classifier: License :: OSI Approved :: MIT License
Classifier: Operating System :: OS Independent
Requires-Python: >=3.8
License-File: LICENSE
